{
  "bg": "https://www.ubackground.com/_ph/4/836078144.jpg",
  "title": "Boku no hero",
  "description": "Nos conte seu nome de herói abaixo e descubra se você é PLUS ULTRA!",
  "logoImg": "https://user-images.githubusercontent.com/45085894/105908243-bce21180-6004-11eb-8422-16404081050a.png",
  "questions": [
    {
      "image": "https://external-content.duckduckgo.com/iu/?u=http%3A%2F%2F49.media.tumblr.com%2F212d77fd7860b463959bb7786d6acc0d%2Ftumblr_o3a7y4a9JI1rvbl4vo5_540.gif&f=1&nofb=1",
      "title": "Qual o nome de herói do Midoriya ?",
      "description": "Essa é bem fácil!",
      "answer": 1,
      "alternatives": [
        "Deku",
        "Destroyer",
        "Deru",
        "OneForALL"
      ]
    },
    {
      "image": "https://external-content.duckduckgo.com/iu/?u=https%3A%2F%2Fmedia.tenor.co%2Fimages%2F32a0316c0ebae66b63cd8197cf8239b2%2Fraw&f=1&nofb=1",
      "title": "Como o poder do allMight é passado a outro portador ?",
      "description": "Essa é bem divertida!",
      "answer": 1,
      "alternatives": [
         "Recebendo um soco do portador",
         "Liberando uma descarga de energia",
         "Consumindo material genetico",
         "Pedindo aos deuses"
      ]
    },
    {
      "image": "https://external-content.duckduckgo.com/iu/?u=https%3A%2F%2Fmedia1.tenor.com%2Fimages%2F508fe7a0908b87ea1de36391094a1049%2Ftenor.gif%3Fitemid%3D9214816&f=1&nofb=1",
      "title": "Qual o herói favorito do Midoriya ?",
      "description": "Essa é bem divertida!",
      "answer": 1,
      "alternatives": [
         "Endeavor",
         "AllMight",
         "Gang Orca"
      ]
    }
  ],
  "external": [
    ""
  ],
  "theme": {
    "colors": {
      "primary": "#144236",
      "secondary": "#113028",
      "mainBg": "#143a30",
      "button": "#FF5722",
      "buttonDisabled": "#c68977",
      "buttonHover": "#ba431f",
      "placeholder": "#abbab0",
      "contrastText": "#FFFFFF",
      "wrong": "#FF5722",
      "success": "#4CAF50"
    },
    "borderRadius": "4px"
  }
}
